bellatrex/LocalMethod_class.py
bellatrex/TreeDissimilarity_class.py
bellatrex/TreeExtraction_class.py
bellatrex/TreeRepresentation_utils.py
bellatrex/__init__.py
bellatrex/gui_plots_code.py
bellatrex/gui_utils.py
bellatrex/plot_tree_patch.py
bellatrex/rule_length_script.py
bellatrex/utilities.py
bellatrex/version.txt
bellatrex/visualisation.py
bellatrex/visualization_extra.py
bellatrex/wrapper_class.py
bellatrex/datasets/__init__.py
bellatrex/datasets/bin_tutorial.csv
bellatrex/datasets/mlc_tutorial.csv
bellatrex/datasets/mtr_tutorial.csv
bellatrex/datasets/regress_tutorial.csv
bellatrex/datasets/surv_tutorial.csv
bellatrex-0.3.0.dist-info/licenses/LICENSE.txt
bellatrex-0.3.0.dist-info/METADATA
bellatrex-0.3.0.dist-info/WHEEL
bellatrex-0.3.0.dist-info/top_level.txt
bellatrex-0.3.0.dist-info/RECORD
