Metadata-Version: 2.4
Name: bellatrex
Version: 0.3.0
Summary: Explaining Random Forest model predictions by Building Explanations through a LocaLly AccuraTe Rule EXtractor
Author-email: Klest Dedja <daneel.olivaw94@gmail.com>
License: Copyright (c) 2024 Klest Dedja
Keywords: explainable AI,rule extraction,random forest,surrogate models
Classifier: License :: OSI Approved :: MIT License
Classifier: Programming Language :: Python :: 3.9
Classifier: Programming Language :: Python :: 3.10
Classifier: Programming Language :: Python :: 3.11
Classifier: Programming Language :: Python :: 3.12
Requires-Python: <3.13,>=3.9
License-File: LICENSE.txt
Requires-Dist: scikit-learn>=1.2
Requires-Dist: threadpoolctl>=3.1
Requires-Dist: scikit-survival<1.0,>=0.22
Requires-Dist: scipy>=1.11
Requires-Dist: pandas>=1.5
Requires-Dist: matplotlib>=3.7
Provides-Extra: dev
Requires-Dist: pytest; extra == "dev"
Requires-Dist: twine; extra == "dev"
Provides-Extra: gui
Requires-Dist: dearpygui<2.0,>=1.6.2; extra == "gui"
Requires-Dist: dearpygui-ext<1.0,>=0.9.5; extra == "gui"
Dynamic: license-file
